hadroid/__init__.py
hadroid/client.py
hadroid/config.py
hadroid/docopt2.py
hadroid/hadroid.py
hadroid/modules/__init__.py
hadroid/modules/base.py
hadroid/modules/coffee.py
hadroid/modules/cron.py
hadroid/modules/eos.py
hadroid/modules/menu.py
hadroid/modules/uservoice.py
hadroid/modules/zenodo_spam.py
hadroid-0.1.19.dist-info/METADATA
hadroid-0.1.19.dist-info/RECORD
hadroid-0.1.19.dist-info/WHEEL
hadroid-0.1.19.dist-info/entry_points.txt
hadroid-0.1.19.dist-info/top_level.txt
