Metadata-Version: 2.1
Name: hadroid
Version: 0.1.19
Summary: A simple Gitter chatbot.
Home-page: https://github.com/hadroid/hadroid
Author: Krzysztof Nowak
Author-email: kn@linux.com
License: GPLv3
Keywords: gitter chatbot
Platform: UNKNOWN
Classifier: Development Status :: 3 - Alpha
Classifier: Intended Audience :: Developers
Classifier: Topic :: Software Development :: Build Tools
Classifier: License :: OSI Approved :: GNU General Public License v3 (GPLv3)
Classifier: Programming Language :: Python :: 3
Classifier: Programming Language :: Python :: 3.3
Classifier: Programming Language :: Python :: 3.4
Classifier: Programming Language :: Python :: 3.5
Provides-Extra: test
Provides-Extra: dev
Requires-Dist: crontab (==0.21.3)
Requires-Dist: cached-property (==1.3.0)
Requires-Dist: docopt (==0.6.2)
Requires-Dist: pytz (==2016.10)
Requires-Dist: requests (==2.11.1)
Requires-Dist: scikit-learn (==0.18.1)
Requires-Dist: numpy (==1.13.0)
Requires-Dist: scipy (==0.19.0)
Requires-Dist: uservoice (==0.0.23)
Requires-Dist: python-dateutil (==2.6.0)
Requires-Dist: beautifulsoup4 (==4.6.0)
Provides-Extra: dev
Requires-Dist: check-manifest; extra == 'dev'
Provides-Extra: test
Requires-Dist: pytest (==3.1.0); extra == 'test'
Requires-Dist: pytest-mock (==1.6.2); extra == 'test'
